MANIFEST.in
README.rst
setup.py
gbdx_task_template/__init__.py
gbdx_task_template/base.py
gbdx_task_template/gbdx_task_interface.py
gbdx_task_template/port.py
gbdx_task_template/task.py
gbdx_task_template.egg-info/PKG-INFO
gbdx_task_template.egg-info/SOURCES.txt
gbdx_task_template.egg-info/dependency_links.txt
gbdx_task_template.egg-info/requires.txt
gbdx_task_template.egg-info/top_level.txt
gbdx_task_template/schemas/__init__.py
gbdx_task_template/schemas/task_descriptor.py
gbdx_task_template/schemas/task_schema.json
gbdx_task_template/test/__init__.py
gbdx_task_template/test/test_base.py
gbdx_task_template/test/test_port.py
gbdx_task_template/test/test_task.py
gbdx_task_template/test/test_template.py